pyvibe/__init__.py
pyvibe/component_interface.py
pyvibe-0.0.5.dist-info/LICENSE
pyvibe-0.0.5.dist-info/METADATA
pyvibe-0.0.5.dist-info/WHEEL
pyvibe-0.0.5.dist-info/top_level.txt
pyvibe-0.0.5.dist-info/RECORD
