Metadata-Version: 2.1
Name: pyvibe
Version: 0.0.5
Summary: Easily create styled web pages with Python
Author-email: Zain Hoda <zain@pycob.com>
Project-URL: Homepage, https://github.com/pycob/pyvibe
Project-URL: Bug Tracker, https://github.com/pycob/pyvibe/issues
Classifier: Programming Language :: Python :: 3
Classifier: License :: OSI Approved :: MIT License
Classifier: Operating System :: OS Independent
Requires-Python: >=3.7
License-File: LICENSE
